setup.py
feature_creation.egg-info/PKG-INFO
feature_creation.egg-info/SOURCES.txt
feature_creation.egg-info/dependency_links.txt
feature_creation.egg-info/top_level.txt
feature_creation_tools/__init__.py
feature_creation_tools/feature_creation_utils.py